CHANGELOG.markdown
COPYING
MANIFEST.in
README.markdown
setup.py
pypln/__init__.py
pypln/api.py
pypln.api.egg-info/PKG-INFO
pypln.api.egg-info/SOURCES.txt
pypln.api.egg-info/dependency_links.txt
pypln.api.egg-info/namespace_packages.txt
pypln.api.egg-info/requires.txt
pypln.api.egg-info/top_level.txt
pypln.api.egg-info/zip-safe
tests/__init__.py
tests/test_pypln.py