Metadata-Version: 1.0
Name: pypln.api
Version: 0.2.0
Summary: Pythonic library to access PyPLN HTTP REST API
Home-page: https://github.com/NAMD/pypln.api
Author: ('\xc3\x81lvaro Justen <alvarojusten@gmail.com>', 'Fl\xc3\xa1vio Amieiro <flavioamieiro@gmail.com>')
Author-email: pypln@googlegroups.com
License: GPL3
Platform: UNKNOWN
